omero_tagsearch/__init__.py
omero_tagsearch/apps.py
omero_tagsearch/forms.py
omero_tagsearch/urls.py
omero_tagsearch/views.py
omero_tagsearch/static/tagsearch/3rd-party/chosen.order.jquery.js
omero_tagsearch/static/tagsearch/3rd-party/jquery.form.js
omero_tagsearch/static/tagsearch/3rd-party/arrayUtilities/jquery.arrayUtilities.js
omero_tagsearch/static/tagsearch/3rd-party/arrayUtilities/jquery.arrayUtilities.min.js
omero_tagsearch/static/tagsearch/3rd-party/chosen/chosen-sprite.png
omero_tagsearch/static/tagsearch/3rd-party/chosen/chosen-sprite@2x.png
omero_tagsearch/static/tagsearch/3rd-party/chosen/chosen.css
omero_tagsearch/static/tagsearch/3rd-party/chosen/chosen.jquery.js
omero_tagsearch/static/tagsearch/3rd-party/chosen/chosen.jquery.min.js
omero_tagsearch/static/tagsearch/3rd-party/chosen/chosen.min.css
omero_tagsearch/static/tagsearch/3rd-party/chosen/chosen.proto.js
omero_tagsearch/static/tagsearch/3rd-party/chosen/chosen.proto.min.js
omero_tagsearch/static/tagsearch/3rd-party/chosen/index.html
omero_tagsearch/static/tagsearch/3rd-party/chosen/index.proto.html
omero_tagsearch/static/tagsearch/3rd-party/chosen/options.html
omero_tagsearch/static/tagsearch/3rd-party/chosen/docsupport/chosen.png
omero_tagsearch/static/tagsearch/3rd-party/chosen/docsupport/oss-credit.png
omero_tagsearch/static/tagsearch/3rd-party/chosen/docsupport/prism.css
omero_tagsearch/static/tagsearch/3rd-party/chosen/docsupport/prism.js
omero_tagsearch/static/tagsearch/3rd-party/chosen/docsupport/style.css
omero_tagsearch/static/tagsearch/css/bootstrap.css
omero_tagsearch/static/tagsearch/css/webtagging_search.css
omero_tagsearch/static/tagsearch/image/folder16.png
omero_tagsearch/static/tagsearch/image/folder_image16.png
omero_tagsearch/static/tagsearch/image/folder_plate16.png
omero_tagsearch/static/tagsearch/image/folder_screen16.png
omero_tagsearch/static/tagsearch/image/icon_user.png
omero_tagsearch/static/tagsearch/image/image16.png
omero_tagsearch/static/tagsearch/image/run16.png
omero_tagsearch-4.3.0.dist-info/LICENSE.txt
omero_tagsearch-4.3.0.dist-info/METADATA
omero_tagsearch-4.3.0.dist-info/WHEEL
omero_tagsearch-4.3.0.dist-info/top_level.txt
omero_tagsearch-4.3.0.dist-info/RECORD
