Metadata-Version: 2.1
Name: omero-tagsearch
Version: 4.3.0
Summary: OMERO webtagging tagsearch app
Home-page: https://github.com/German-BioImaging/omero-tagsearch
Author: D.P.W. Russell
Author-email: dpwrussell@gmail.com
Maintainer: Tom Boissonnet
Maintainer-email: tom.boissonnet@hhu.de
License: AGPL-3.0
Download-URL: https://github.com/German-BioImaging/omero-tagsearch/archive/v4.3.0.tar.gz
Keywords: OMERO.web,webtagging,tagsearch
Platform: UNKNOWN
Classifier: Development Status :: 5 - Production/Stable
Classifier: Environment :: Web Environment
Classifier: Framework :: Django
Classifier: Intended Audience :: End Users/Desktop
Classifier: Intended Audience :: Science/Research
Classifier: License :: OSI Approved :: GNU Affero General Public License v3
Classifier: Natural Language :: English
Classifier: Operating System :: OS Independent
Classifier: Programming Language :: JavaScript
Classifier: Programming Language :: Python :: 3
Classifier: Topic :: Internet :: WWW/HTTP
Classifier: Topic :: Internet :: WWW/HTTP :: Dynamic Content
Classifier: Topic :: Internet :: WWW/HTTP :: WSGI
Classifier: Topic :: Scientific/Engineering :: Visualization
Classifier: Topic :: Software Development :: Libraries :: Application Frameworks
Classifier: Topic :: Text Processing :: Markup :: HTML
Obsoletes: omero_webtagging_tagsearch
Requires-Python: >=3
License-File: LICENSE.txt
Requires-Dist: omero-web>=5.6.0
